<?xml version="1.0"?>

		<bustime-response>
				
			<stop>
			<stpid>14483</stpid>
			<stpnm>1100 S Columbus (Pedestrian Underpass)</stpnm>
			<lat>41.869389054621</lat>
			<lon>-87.620467543602</lon>
			</stop>
				
			<stop>
			<stpid>7137</stpid>
			<stpnm>5000 S Lake Park</stpnm>
			<lat>41.804462026999</lat>
			<lon>-87.588517069817</lon>
			</stop>
				
			<stop>
			<stpid>1522</stpid>
			<stpnm>5200 S S Hyde Park</stpnm>
			<lat>41.800831044205</lat>
			<lon>-87.584461569786</lon>
			</stop>
				
			<stop>
			<stpid>1519</stpid>
			<stpnm>5440 S S Hyde Park</stpnm>
			<lat>41.796775936972</lat>
			<lon>-87.583925127983</lon>
			</stop>
				
			<stop>
			<stpid>1514</stpid>
			<stpnm>5800 S Stony Island</stpnm>
			<lat>41.789636885138</lat>
			<lon>-87.586612701416</lon>
			</stop>
				
			<stop>
			<stpid>5312</stpid>
			<stpnm>67th Street &amp; Bennett</stpnm>
			<lat>41.773436087807</lat>
			<lon>-87.579075694084</lon>
			</stop>
				
			<stop>
			<stpid>7040</stpid>
			<stpnm>67th Street &amp; Clyde</stpnm>
			<lat>41.773484096216</lat>
			<lon>-87.574000954628</lon>
			</stop>
				
			<stop>
			<stpid>5315</stpid>
			<stpnm>67th Street &amp; Cornell Drive</stpnm>
			<lat>41.773364075128</lat>
			<lon>-87.585663199425</lon>
			</stop>
				
			<stop>
			<stpid>7038</stpid>
			<stpnm>67th Street &amp; Crandon</stpnm>
			<lat>41.773532104588</lat>
			<lon>-87.569983005524</lon>
			</stop>
				
			<stop>
			<stpid>5313</stpid>
			<stpnm>67th Street &amp; Cregier</stpnm>
			<lat>41.773404082182</lat>
			<lon>-87.581398487091</lon>
			</stop>
				
			<stop>
			<stpid>5314</stpid>
			<stpnm>67th Street &amp; East End</stpnm>
			<lat>41.773384078658</lat>
			<lon>-87.583823204041</lon>
			</stop>
				
			<stop>
			<stpid>5311</stpid>
			<stpnm>67th Street &amp; Jeffery</stpnm>
			<lat>41.773472094117</lat>
			<lon>-87.576811909676</lon>
			</stop>
				
			<stop>
			<stpid>15391</stpid>
			<stpnm>67th Street &amp; Oglesby</stpnm>
			<lat>41.773556108761</lat>
			<lon>-87.568228840828</lon>
			</stop>
				
			<stop>
			<stpid>15147</stpid>
			<stpnm>67th Street &amp; Paxton</stpnm>
			<lat>41.773516101801</lat>
			<lon>-87.571828365326</lon>
			</stop>
				
			<stop>
			<stpid>2601</stpid>
			<stpnm>79th Street &amp; Brandon</stpnm>
			<lat>41.752016753906</lat>
			<lon>-87.54698574543</lon>
			</stop>
				
			<stop>
			<stpid>4883</stpid>
			<stpnm>Balbo &amp; Columbus</stpnm>
			<lat>41.873243835199</lat>
			<lon>-87.621036171913</lon>
			</stop>
				
			<stop>
			<stpid>4884</stpid>
			<stpnm>Balbo &amp; Michigan</stpnm>
			<lat>41.873187912583</lat>
			<lon>-87.624024152756</lon>
			</stop>
				
			<stop>
			<stpid>1524</stpid>
			<stpnm>E Hyde Park &amp; Cornell</stpnm>
			<lat>41.80250260149</lat>
			<lon>-87.586698532104</lon>
			</stop>
				
			<stop>
			<stpid>1523</stpid>
			<stpnm>E Hyde Park &amp; East End</stpnm>
			<lat>41.802510599267</lat>
			<lon>-87.585695385933</lon>
			</stop>
				
			<stop>
			<stpid>5040</stpid>
			<stpnm>Lake Park &amp; 47th Street Terminal</stpnm>
			<lat>41.8091084251</lat>
			<lon>-87.591628432274</lon>
			</stop>
				
			<stop>
			<stpid>5039</stpid>
			<stpnm>Lake Park &amp; 48th Street</stpnm>
			<lat>41.808064814251</lat>
			<lon>-87.590485811234</lon>
			</stop>
				
			<stop>
			<stpid>5038</stpid>
			<stpnm>Lake Park &amp; 49th Street</stpnm>
			<lat>41.805813595796</lat>
			<lon>-87.589091062546</lon>
			</stop>
				
			<stop>
			<stpid>5037</stpid>
			<stpnm>Lake Park &amp; E. Hyde Park Blvd</stpnm>
			<lat>41.802874497061</lat>
			<lon>-87.587884068489</lon>
			</stop>
				
			<stop>
			<stpid>14485</stpid>
			<stpnm>Michigan &amp; Congress</stpnm>
			<lat>41.875520643017</lat>
			<lon>-87.624131441116</lon>
			</stop>
				
			<stop>
			<stpid>1121</stpid>
			<stpnm>Michigan &amp; E. Wacker</stpnm>
			<lat>41.888045629768</lat>
			<lon>-87.624405026436</lon>
			</stop>
				
			<stop>
			<stpid>76</stpid>
			<stpnm>Michigan &amp; Jackson</stpnm>
			<lat>41.878124892161</lat>
			<lon>-87.624158263206</lon>
			</stop>
				
			<stop>
			<stpid>2188</stpid>
			<stpnm>Michigan &amp; Madison</stpnm>
			<lat>41.882366555435</lat>
			<lon>-87.624174356461</lon>
			</stop>
				
			<stop>
			<stpid>15241</stpid>
			<stpnm>Michigan &amp; Monroe</stpnm>
			<lat>41.88066912511</lat>
			<lon>-87.624195814133</lon>
			</stop>
				
			<stop>
			<stpid>1119</stpid>
			<stpnm>Michigan &amp; Randolph</stpnm>
			<lat>41.884686969581</lat>
			<lon>-87.624351382256</lon>
			</stop>
				
			<stop>
			<stpid>1120</stpid>
			<stpnm>Michigan &amp; South Water</stpnm>
			<lat>41.886699790703</lat>
			<lon>-87.624415755272</lon>
			</stop>
				
			<stop>
			<stpid>1521</stpid>
			<stpnm>S Hyde Park &amp; 53rd Street</stpnm>
			<lat>41.799455375836</lat>
			<lon>-87.584000229836</lon>
			</stop>
				
			<stop>
			<stpid>1520</stpid>
			<stpnm>S Hyde Park &amp; 54th Street</stpnm>
			<lat>41.798339623115</lat>
			<lon>-87.583984136581</lon>
			</stop>
				
			<stop>
			<stpid>1518</stpid>
			<stpnm>S Hyde Park &amp; 55th Street</stpnm>
			<lat>41.795452172847</lat>
			<lon>-87.583903670311</lon>
			</stop>
				
			<stop>
			<stpid>1517</stpid>
			<stpnm>S Hyde Park &amp; 56th Street</stpnm>
			<lat>41.793336493052</lat>
			<lon>-87.583871483803</lon>
			</stop>
				
			<stop>
			<stpid>7035</stpid>
			<stpnm>S. Shore Drive &amp; 68th Street</stpnm>
			<lat>41.771951810121</lat>
			<lon>-87.566555142403</lon>
			</stop>
				
			<stop>
			<stpid>7034</stpid>
			<stpnm>S. Shore Drive &amp; 69th Street</stpnm>
			<lat>41.769799346422</lat>
			<lon>-87.56650686264</lon>
			</stop>
				
			<stop>
			<stpid>7033</stpid>
			<stpnm>S. Shore Drive &amp; 70th Street</stpnm>
			<lat>41.768395004966</lat>
			<lon>-87.566469311714</lon>
			</stop>
				
			<stop>
			<stpid>7032</stpid>
			<stpnm>S. Shore Drive &amp; 71st Street</stpnm>
			<lat>41.766878601752</lat>
			<lon>-87.566421031952</lon>
			</stop>
				
			<stop>
			<stpid>7030</stpid>
			<stpnm>S. Shore Drive &amp; 72nd Street</stpnm>
			<lat>41.765950337244</lat>
			<lon>-87.562419176102</lon>
			</stop>
				
			<stop>
			<stpid>7029</stpid>
			<stpnm>S. Shore Drive &amp; 73rd Street</stpnm>
			<lat>41.764165791023</lat>
			<lon>-87.560665011406</lon>
			</stop>
				
			<stop>
			<stpid>7028</stpid>
			<stpnm>S. Shore Drive &amp; 74th Street</stpnm>
			<lat>41.762481229881</lat>
			<lon>-87.558996677399</lon>
			</stop>
				
			<stop>
			<stpid>7027</stpid>
			<stpnm>S. Shore Drive &amp; 75th Street</stpnm>
			<lat>41.760768614073</lat>
			<lon>-87.557296156883</lon>
			</stop>
				
			<stop>
			<stpid>7026</stpid>
			<stpnm>S. Shore Drive &amp; 76th Street</stpnm>
			<lat>41.758983923734</lat>
			<lon>-87.555520534515</lon>
			</stop>
				
			<stop>
			<stpid>7025</stpid>
			<stpnm>S. Shore Drive &amp; 77th Street</stpnm>
			<lat>41.757271214587</lat>
			<lon>-87.553675174713</lon>
			</stop>
				
			<stop>
			<stpid>7024</stpid>
			<stpnm>S. Shore Drive &amp; 78th Street</stpnm>
			<lat>41.755498432448</lat>
			<lon>-87.551776170731</lon>
			</stop>
				
			<stop>
			<stpid>7022</stpid>
			<stpnm>S. Shore Drive &amp; 79th Street</stpnm>
			<lat>41.752268881798</lat>
			<lon>-87.548300027847</lon>
			</stop>
				
			<stop>
			<stpid>7023</stpid>
			<stpnm>S. Shore Drive &amp; Cheltenham</stpnm>
			<lat>41.753613547165</lat>
			<lon>-87.549737691879</lon>
			</stop>
				
			<stop>
			<stpid>7031</stpid>
			<stpnm>S. Shore Drive &amp; Coles</stpnm>
			<lat>41.766338449469</lat>
			<lon>-87.565101385117</lon>
			</stop>
				
			<stop>
			<stpid>1515</stpid>
			<stpnm>Stony Island &amp; 57th Drive</stpnm>
			<lat>41.791340731091</lat>
			<lon>-87.586660981178</lon>
			</stop>
				
			<stop>
			<stpid>1513</stpid>
			<stpnm>Stony Island &amp; 59th Street</stpnm>
			<lat>41.7880969854</lat>
			<lon>-87.586585879326</lon>
			</stop>
				
			<stop>
			<stpid>1512</stpid>
			<stpnm>Stony Island &amp; 60th Street</stpnm>
			<lat>41.786005062346</lat>
			<lon>-87.586537599564</lon>
			</stop>
				
			<stop>
			<stpid>1511</stpid>
			<stpnm>Stony Island &amp; 61st Street</stpnm>
			<lat>41.783929071227</lat>
			<lon>-87.586494684219</lon>
			</stop>
				
			<stop>
			<stpid>1510</stpid>
			<stpnm>Stony Island &amp; 62nd Street</stpnm>
			<lat>41.782825048572</lat>
			<lon>-87.586457133293</lon>
			</stop>
				
			<stop>
			<stpid>5320</stpid>
			<stpnm>Stony Island &amp; 63rd Street</stpnm>
			<lat>41.780468936655</lat>
			<lon>-87.586414217949</lon>
			</stop>
				
			<stop>
			<stpid>5318</stpid>
			<stpnm>Stony Island &amp; 64th Street</stpnm>
			<lat>41.778772802499</lat>
			<lon>-87.586360573769</lon>
			</stop>
				
			<stop>
			<stpid>5317</stpid>
			<stpnm>Stony Island &amp; 65th Street</stpnm>
			<lat>41.777008615368</lat>
			<lon>-87.586215734482</lon>
			</stop>
				
			<stop>
			<stpid>5316</stpid>
			<stpnm>Stony Island &amp; Marquette Rd</stpnm>
			<lat>41.77505635173</lat>
			<lon>-87.586103081703</lon>
			</stop>
				
			<stop>
			<stpid>3954</stpid>
			<stpnm>Wacker (Upper) &amp; Columbus</stpnm>
			<lat>41.887829977938</lat>
			<lon>-87.620955705643</lon>
			</stop>
				
			<stop>
			<stpid>14222</stpid>
			<stpnm>Wacker (Upper) &amp; Columbus</stpnm>
			<lat>41.888029655583</lat>
			<lon>-87.620821595192</lon>
			</stop>
				
			<stop>
			<stpid>3953</stpid>
			<stpnm>Wacker (Upper) &amp; Stetson</stpnm>
			<lat>41.887989720104</lat>
			<lon>-87.62191593647</lon>
			</stop>

		</bustime-response>

		
